LLMFunctionObjects/Chat.py
LLMFunctionObjects/Configuration.py
LLMFunctionObjects/Evaluator.py
LLMFunctionObjects/EvaluatorChat.py
LLMFunctionObjects/EvaluatorChatGPT.py
LLMFunctionObjects/EvaluatorChatPaLM.py
LLMFunctionObjects/Functor.py
LLMFunctionObjects/LLMFunctions.py
LLMFunctionObjects/SubParser.py
LLMFunctionObjects/__init__.py
LLMFunctionObjects-0.1.7.dist-info/LICENSE
LLMFunctionObjects-0.1.7.dist-info/METADATA
LLMFunctionObjects-0.1.7.dist-info/WHEEL
LLMFunctionObjects-0.1.7.dist-info/top_level.txt
LLMFunctionObjects-0.1.7.dist-info/RECORD
