Metadata-Version: 2.1
Name: LLMFunctionObjects
Version: 0.1.7
Summary: Large Language Models (LLMs) functions package.
Home-page: https://github.com/antononcube/Python-packages/tree/main/LLMFunctionObjects
Author: Anton Antonov
Author-email: antononcube@posteo.net
Keywords: llm,llm functions,llm functors,large language models,openai,chatgpt,palm,ml,machine learning
Classifier: Intended Audience :: Science/Research
Classifier: Intended Audience :: Developers
Classifier: Programming Language :: Python :: 3
Classifier: License :: OSI Approved :: BSD License
Classifier: Intended Audience :: Science/Research
Classifier: Intended Audience :: Developers
Classifier: Operating System :: OS Independent
Requires-Python: >=3.7
License-File: LICENSE
Requires-Dist: google-generativeai >=0.3.2
Requires-Dist: openai >=1.3.0
